scenario_assessment/__init__.py
scenario_assessment/filter.py
scenario_assessment/filter_tools.py
scenario_assessment-0.1.3.dist-info/LICENSE
scenario_assessment-0.1.3.dist-info/METADATA
scenario_assessment-0.1.3.dist-info/WHEEL
scenario_assessment-0.1.3.dist-info/RECORD
